lis/__init__.py
lis/settings.py
lis/streaming.py
lis/collections/__init__.py
lis/decorators/__init__.py
lis-0.0.5.dist-info/LICENSE
lis-0.0.5.dist-info/METADATA
lis-0.0.5.dist-info/WHEEL
lis-0.0.5.dist-info/top_level.txt
lis-0.0.5.dist-info/RECORD
