Metadata-Version: 2.1
Name: lis
Version: 0.0.5
Summary: Life is short, use `lis`
Home-page: https://github.com/Marcnuth/lis
Author: Marcnuth
Author-email: hxianxian@gmail.com
License: Apache License 2.0
Platform: UNKNOWN
Classifier: Topic :: Scientific/Engineering :: Artificial Intelligence
Classifier: Topic :: Software Development :: Libraries
Classifier: Programming Language :: Python :: 3
